smashed/__init__.py
smashed/py.typed
smashed/base/__init__.py
smashed/base/abstract.py
smashed/base/interfaces.py
smashed/base/mappers.py
smashed/base/pipeline.py
smashed/base/recipes.py
smashed/base/types.py
smashed/base/views.py
smashed/contrib/__init__.py
smashed/contrib/squad.py
smashed/contrib/sse.py
smashed/interfaces/__init__.py
smashed/interfaces/huggingface.py
smashed/interfaces/simple.py
smashed/mappers/__init__.py
smashed/mappers/batchers.py
smashed/mappers/cache.py
smashed/mappers/collators.py
smashed/mappers/converters.py
smashed/mappers/debug.py
smashed/mappers/decoding.py
smashed/mappers/fields.py
smashed/mappers/filters.py
smashed/mappers/glom.py
smashed/mappers/loaders.py
smashed/mappers/masks.py
smashed/mappers/multiseq.py
smashed/mappers/prompting.py
smashed/mappers/promptsource.py
smashed/mappers/shape.py
smashed/mappers/text.py
smashed/mappers/tokenize.py
smashed/mappers/types.py
smashed/recipes/__init__.py
smashed/recipes/collators.py
smashed/recipes/prompting.py
smashed/recipes/promptsource.py
smashed/utils/__init__.py
smashed/utils/caching.py
smashed/utils/convert.py
smashed/utils/install_blingfire_macos.py
smashed/utils/shape_utils.py
smashed/utils/version.py
smashed/utils/warnings.py
smashed/utils/wordsplitter.py
smashed/utils/io_utils/__init__.py
smashed/utils/io_utils/closures.py
smashed/utils/io_utils/compression.py
smashed/utils/io_utils/io_wrappers.py
smashed/utils/io_utils/multipath.py
smashed/utils/io_utils/operations.py
smashed-0.21.5.dist-info/LICENSE
smashed-0.21.5.dist-info/METADATA
smashed-0.21.5.dist-info/WHEEL
smashed-0.21.5.dist-info/top_level.txt
smashed-0.21.5.dist-info/RECORD
