Metadata-Version: 2.1
Name: smashed
Version: 0.21.5
Summary: SMASHED is a toolkit designed to apply transformations to samples in datasets, such as fields extraction, tokenization, prompting, batching, and more. Supports datasets from Huggingface, torchdata iterables, or simple lists of dictionaries.
Author-email: Allen Institute for Artificial Intelligence <contact@allenai.org>, Luca Soldaini <luca@soldaini.net>, Kyle Lo <kylel@allenai.org>
Maintainer-email: Luca Soldaini <luca@soldaini.net>
License: Apache-2.0
Project-URL: Homepage, https://github.com/allenai/smashed
Project-URL: Repository, https://github.com/allenai/smashed
Project-URL: Bug Tracker, https://github.com/allenai/smashed/issues
Keywords: mappers,pytorch,torch,huggingface,transformers,datasets,dict,pipeline,preprocessing,nlp,natural language processing,text,prompting,prefix tuning,in context learning
Classifier: Development Status :: 4 - Beta
Classifier: License :: OSI Approved :: Apache Software License
Classifier: Operating System :: OS Independent
Classifier: Programming Language :: Python :: 3
Classifier: Topic :: Scientific/Engineering :: Artificial Intelligence
Classifier: Topic :: Software Development :: Libraries :: Python Modules
Classifier: Topic :: Utilities
Classifier: Typing :: Typed
Requires-Python: >=3.8
License-File: LICENSE
Requires-Dist: necessary >=0.4.3
Requires-Dist: trouting >=0.3.3
Requires-Dist: ftfy >=6.1.1
Requires-Dist: platformdirs >=2.5.0
Requires-Dist: glom >=21.0.0
Requires-Dist: Jinja2 >=3.0.3
Requires-Dist: numpy >=1.19.5
Provides-Extra: all
Requires-Dist: smashed[dev] ; extra == 'all'
Requires-Dist: smashed[torch] ; extra == 'all'
Requires-Dist: smashed[datasets] ; extra == 'all'
Requires-Dist: smashed[torchdata] ; extra == 'all'
Requires-Dist: smashed[remote] ; extra == 'all'
Requires-Dist: smashed[prompting] ; extra == 'all'
Provides-Extra: datasets
Requires-Dist: smashed[torch] ; extra == 'datasets'
Requires-Dist: transformers >=4.5 ; extra == 'datasets'
Requires-Dist: datasets >=2.8.0 ; extra == 'datasets'
Requires-Dist: dill >=0.3.0 ; extra == 'datasets'
Provides-Extra: dev
Requires-Dist: black[jupyter] >=21.12b0 ; extra == 'dev'
Requires-Dist: isort >=5.8.0 ; extra == 'dev'
Requires-Dist: mypy >=0.971 ; extra == 'dev'
Requires-Dist: pytest >=5.2 ; extra == 'dev'
Requires-Dist: ipython >=8.4.0 ; extra == 'dev'
Requires-Dist: autopep8 >=1.7.0 ; extra == 'dev'
Requires-Dist: flake8 >=5.0 ; extra == 'dev'
Requires-Dist: ipdb >=0.13.0 ; extra == 'dev'
Requires-Dist: flake8-pyi >=22.8.1 ; extra == 'dev'
Requires-Dist: Flake8-pyproject >=1.1.0 ; extra == 'dev'
Requires-Dist: moto[all,ec2,s3] >=4.0.0 ; extra == 'dev'
Provides-Extra: prompting
Requires-Dist: smashed[torch] ; extra == 'prompting'
Requires-Dist: transformers >=4.5 ; extra == 'prompting'
Requires-Dist: promptsource >=0.2.3 ; extra == 'prompting'
Requires-Dist: blingfire >=0.1.8 ; extra == 'prompting'
Provides-Extra: remote
Requires-Dist: smart-open >=5.2.1 ; extra == 'remote'
Requires-Dist: boto3 >=1.25.5 ; extra == 'remote'
Provides-Extra: torch
Requires-Dist: torch >=1.9 ; extra == 'torch'
Provides-Extra: torchdata
Requires-Dist: torch >=1.13.1 ; extra == 'torchdata'
Requires-Dist: torchdata >=0.5.1 ; extra == 'torchdata'
